PyCMLutil/__init__.py
PyCMLutil/animation/__init__.py
PyCMLutil/animation/pymyovent_ventricle.py
PyCMLutil/curve_fitting/__init__.py
PyCMLutil/curve_fitting/curve_fitting.py
PyCMLutil/plots/__init__.py
PyCMLutil/plots/fv_plots.py
PyCMLutil/plots/multi_panel.py
PyCMLutil/plots/multi_panel_cat.py
PyCMLutil/plots/pCa_plots.py
PyCMLutil/plots/pv_plots.py
demos/__init__.py
demos/demos_code.py
demos/demos_plots/__init__.py
demos/demos_plots/demos_multi_panel/__init__.py
demos/demos_plots/demos_multi_panel/create_test_data.py
demos/demos_plots/demos_multi_panel/demos_multi_panel_code.py
test/__init__.py
test/test_animation.py
test/test_cat.py
test/test_pv.py
PyCMLutil-0.0.2.dist-info/LICENSE
PyCMLutil-0.0.2.dist-info/METADATA
PyCMLutil-0.0.2.dist-info/WHEEL
PyCMLutil-0.0.2.dist-info/top_level.txt
PyCMLutil-0.0.2.dist-info/RECORD
