Metadata-Version: 2.1
Name: PyCMLutil
Version: 0.0.2
Summary: A usefule python package for generating sientific figures.
Home-page: https://github.com/Campbell-Muscle-Lab/PyCMLutilities
Author: Kenneth S. Campbell
Author-email: hossein.sharifi@uky.edu
License: UNKNOWN
Platform: UNKNOWN
Classifier: Programming Language :: Python :: 3.6
Classifier: License :: OSI Approved :: GNU General Public License v3 or later (GPLv3+)
Classifier: Operating System :: OS Independent
Requires-Python: >=3.6
Requires-Dist: numpy (>=1.16)
Requires-Dist: pandas (>=0.24)
Requires-Dist: matplotlib (>=3.0)
